Metadata-Version: 1.1
Name: thebot
Version: 0.4.1
Summary: ()
Home-page: http://github.com/svetlyak40wt/thebot/
Author: Alexander Artemenko
Author-email: svetlyak.40wt@gmail.com
License: New BSD License
Keywords: chat irc xmpp basecamp jira fun
Platform: UNKNOWN
Classifier: Development Status :: 4 - Beta
Classifier: Environment :: Console
Classifier: Intended Audience :: Developers
Classifier: Intended Audience :: System Administrators
Classifier: License :: OSI Approved :: BSD License
Classifier: Programming Language :: Python
Classifier: Programming Language :: Python :: 3
